freddata/__init__.py
rhofred-0.3.0.dist-info/licenses/LICENSE
rhofred-0.3.0.dist-info/METADATA
rhofred-0.3.0.dist-info/WHEEL
rhofred-0.3.0.dist-info/top_level.txt
rhofred-0.3.0.dist-info/RECORD
