Metadata-Version: 2.4
Name: rhofred
Version: 0.3.0
Summary: Data from fred
Author-email: rhozhang <rhozhang@163.com>
License-Expression: MIT
Project-URL: Homepage, https://github.com/rhozhang/rhofred
Project-URL: Issues, https://github.com/rhozhang/rhofred/issues
Keywords: fred,data
Classifier: Programming Language :: Python :: 3
Classifier: Operating System :: OS Independent
Requires-Python: >=3.12
License-File: LICENSE
Requires-Dist: polars
Dynamic: license-file
